{
  "2026-AACR-RAS-Meeting_AXL-Poster.pdf": {
    "source_url": "https://arcusbio.com/wp-content/uploads/2026/03/2026-AACR-RAS-Meeting_AXL-Poster.pdf",
    "title": "AB801, a Potent and Selective Clinical-Stage AXL Inhibitor, Enhances the Anti-Tumor Efficacy and Duration of Response of KRAS Inhibitors",
    "date": "2026-03-01",
    "doc_type": "poster",
    "sha256": "7fe9847548578f3fff5e5bc267cd986d4377c852cc3a5ad07759b954b50a1aa6",
    "file_size_bytes": 1701499,
    "scraped_at": "2026-03-25T16:24:17.450828+00:00",
    "source_page": "https://arcusbio.com/our-science/publications/",
    "page_type": "publications"
  },
  "AAAAI-2026-X2-Poster.pdf": {
    "source_url": "https://arcusbio.com/wp-content/uploads/2026/03/AAAAI-2026-X2-Poster.pdf",
    "title": "Inhibition of Mast Cell Specific MRGPRX2 in Dermal and Mucosal Diseases",
    "date": "2026-03-01",
    "doc_type": "poster",
    "sha256": "c3389d21086891571c5fcf81fd59a9284eea2c192fe84dd07f7edfa8e6a065b4",
    "file_size_bytes": 1660682,
    "scraped_at": "2026-03-25T16:24:17.577461+00:00",
    "source_page": "https://arcusbio.com/our-science/publications/",
    "page_type": "publications"
  },
  "2026_AACR-IO_ARC-9_20260206_DisclosureCopy.pdf": {
    "source_url": "https://arcusbio.com/wp-content/uploads/2026/02/2026_AACR-IO_ARC-9_20260206_DisclosureCopy.pdf",
    "title": "Clinical benefit from treatment of advanced MSS mCRC with the A2aR/A2bR antagonist etrumadenant is associated with adenosine-mediated T-cell exclusion and enhancement of the effectiveness of immunotherapy",
    "date": "2026-02-01",
    "doc_type": "poster",
    "sha256": "5ea3a3c7478d5d14f8cad0ed48a81e33b0c6650e389905467770e39647e61604",
    "file_size_bytes": 14455768,
    "scraped_at": "2026-03-25T16:24:18.003877+00:00",
    "source_page": "https://arcusbio.com/our-science/publications/",
    "page_type": "publications"
  },
  "2026-AACR-IO-TIGIT-CD155-Poster-FINAL.pdf": {
    "source_url": "https://arcusbio.com/wp-content/uploads/2026/02/2026-AACR-IO-TIGIT-CD155-Poster-FINAL.pdf",
    "title": "TIGIT Blockade Enhances the Effect of Anti-PD-1 Against CD155hi Expressing Tumors in Mouse and Human Models",
    "date": "2026-02-01",
    "doc_type": "poster",
    "sha256": "4d95d917945d81f10671b1b6037aaac36a96f97ba0c87678370be0bcc51d35a9",
    "file_size_bytes": 2705855,
    "scraped_at": "2026-03-25T16:24:18.226060+00:00",
    "source_page": "https://arcusbio.com/our-science/publications/",
    "page_type": "publications"
  },
  "SITC_ATP_signature_Poster_09262025.pdf": {
    "source_url": "https://arcusbio.com/wp-content/uploads/2025/11/SITC_ATP_signature_Poster_09262025.pdf",
    "title": "Exogenous ATP Drives Transcriptomic Changes Related to DC Activation that are Elevated by Neoadjuvant Chemoradiotherapy in Esophageal Cancer",
    "date": "2025-11-01",
    "doc_type": "poster",
    "sha256": "6dc1b95ae19bc8bb844524117684da589976ecb86e2b1b6c96242c993866d3b9",
    "file_size_bytes": 4714494,
    "scraped_at": "2026-03-25T16:24:18.472139+00:00",
    "source_page": "https://arcusbio.com/our-science/publications/",
    "page_type": "publications"
  },
  "2025-SITC-ARC-25-Poster_Final.pdf": {
    "source_url": "https://arcusbio.com/wp-content/uploads/2025/11/2025-SITC-ARC-25-Poster_Final.pdf",
    "title": "Peripheral Pharmacodynamic Analysis of Anti-CD39 Monoclonal Antibody AB598 in a First-In-Human Phase I Trial in Patients with Advanced Solid Tumors",
    "date": "2025-11-01",
    "doc_type": "poster",
    "sha256": "df7c08b3e0eb958fbceb7d130643c17a83bc02eee9c822828d22c2db4537bfb5",
    "file_size_bytes": 4111129,
    "scraped_at": "2026-03-25T16:24:18.689976+00:00",
    "source_page": "https://arcusbio.com/our-science/publications/",
    "page_type": "publications"
  },
  "20251014-SITC-ARC-25-Tumor-Biomarker-Poster_FINAL.pdf": {
    "source_url": "https://arcusbio.com/wp-content/uploads/2025/11/20251014-SITC-ARC-25-Tumor-Biomarker-Poster_FINAL.pdf",
    "title": "Tumor Biomarker Analysis of Anti-CD39 Monoclonal Antibody AB598 in a First-In-Human Phase I Trial in Patients with Advanced Solid Tumors",
    "date": "2025-11-01",
    "doc_type": "poster",
    "sha256": "f8eeffe92aed31cf7b12c124637d50f1dd982057c346bff9253770ce62b70610",
    "file_size_bytes": 1867752,
    "scraped_at": "2026-03-25T16:24:18.788005+00:00",
    "source_page": "https://arcusbio.com/our-science/publications/",
    "page_type": "publications"
  },
  "TNF-poster-ACR-Convergence-2025-092625.pdf": {
    "source_url": "https://arcusbio.com/wp-content/uploads/2025/10/TNF-poster-ACR-Convergence-2025-092625.pdf",
    "title": "TNF Inhibition with Small-molecule Agents Results in Amelioration of Inflammation Similar to that of Anti-TNF Biologics While Preserving TNFR2 Signaling and Maintaining a Suppressive Regulatory T cell Phenotype",
    "date": "2025-10-01",
    "doc_type": "poster",
    "sha256": "bb2eae41bfd60a12c47f858ad40b89dd45c593e6d555ec50114a411d920834e8",
    "file_size_bytes": 997170,
    "scraped_at": "2026-03-25T16:24:18.960640+00:00",
    "source_page": "https://arcusbio.com/our-science/publications/",
    "page_type": "publications"
  },
  "2025_ULK_Triple-Meeting-Poster.pdf": {
    "source_url": "https://arcusbio.com/wp-content/uploads/2025/10/2025_ULK_Triple-Meeting-Poster.pdf",
    "title": "Inhibition of ULK1/2-Mediated Autophagy Enhances Responses to RAS Inhibition and Augments Antigen-Specific T Cell Cytotoxicity",
    "date": "2025-10-01",
    "doc_type": "poster",
    "sha256": "892ee17bd992f6b347c9c22e73b97f5ba2b7a2dcec94dd7d92b9b255904799d4",
    "file_size_bytes": 1579158,
    "scraped_at": "2026-03-25T16:24:19.065795+00:00",
    "source_page": "https://arcusbio.com/our-science/publications/",
    "page_type": "publications"
  },
  "2025-Triple-Meeting_AXL-Poster.pdf": {
    "source_url": "https://arcusbio.com/wp-content/uploads/2025/10/2025-Triple-Meeting_AXL-Poster.pdf",
    "title": "AXL Inhibitor AB801 Increases the Anti-Tumor Efficacy of KRAS Inhibition",
    "date": "2025-10-01",
    "doc_type": "poster",
    "sha256": "24459dcfd4c1c8ede3cc2c34e0f4d35d8532d608d2ec67bbe78c69dc646931d0",
    "file_size_bytes": 925990,
    "scraped_at": "2026-03-25T16:24:19.165169+00:00",
    "source_page": "https://arcusbio.com/our-science/publications/",
    "page_type": "publications"
  },
  "ENA_2025_ARC-20_Poster_Draft_20250924_revised_external.pdf": {
    "source_url": "https://arcusbio.com/wp-content/uploads/2025/10/ENA_2025_ARC-20_Poster_Draft_20250924_revised_external.pdf",
    "title": "Erythropoietin (EPO) is a Pharmacodynamic Biomarker for Systemic HIF-2\u237a Inhibition that Correlates with the Clinical Activity of Casdatifan",
    "date": "2025-10-01",
    "doc_type": "poster",
    "sha256": "0392a33cb12fc2b8aa3e5095fa0a0c96a366016c503b0d7d4fb711f2321c947d",
    "file_size_bytes": 720132,
    "scraped_at": "2026-03-25T16:24:19.296189+00:00",
    "source_page": "https://arcusbio.com/our-science/publications/",
    "page_type": "publications"
  },
  "AB598-PKPD-ENA_poster_8Oct2025.pdf": {
    "source_url": "https://arcusbio.com/wp-content/uploads/2025/10/AB598-PKPD-ENA_poster_8Oct2025.pdf",
    "title": "Clinical Pharmacokinetic/Pharmacodynamic Relationship for AB598, an anti-CD39 Monoclonal Antibody in Patients with Advanced Cancer",
    "date": "2025-10-01",
    "doc_type": "poster",
    "sha256": "5fa487b29983abd614ac3f26f1e22ca0828bd84931bc8837b67fd58bf27ed37f",
    "file_size_bytes": 577863,
    "scraped_at": "2026-03-25T16:24:19.379244+00:00",
    "source_page": "https://arcusbio.com/our-science/publications/",
    "page_type": "publications"
  },
  "2025_EAACI_BFX_Poster_final.pdf": {
    "source_url": "https://arcusbio.com/wp-content/uploads/2025/06/2025_EAACI_BFX_Poster_final.pdf",
    "title": "MRGPRX2 Specific Activation Signature is Enriched in Atopic Dermatitis Skin Lesions and Wheals from Chronic Spontaneous Urticaria Skin Compared to Adjacent Healthy Skin",
    "date": "2025-06-01",
    "doc_type": "poster",
    "sha256": "17db78a73fb8264b443de61fbc2bcbf90eea734f629e4004c2bf485a2dda2377",
    "file_size_bytes": 4409083,
    "scraped_at": "2026-03-25T16:24:19.614655+00:00",
    "source_page": "https://arcusbio.com/our-science/publications/",
    "page_type": "publications"
  },
  "2025-EAACI-Poster-Biology-final-0625.pdf": {
    "source_url": "https://arcusbio.com/wp-content/uploads/2025/06/2025-EAACI-Poster-Biology-final-0625.pdf",
    "title": "Targeting MRGPRX2 for the Treatment of Mast Cell-Driven Diseases",
    "date": "2025-06-01",
    "doc_type": "poster",
    "sha256": "93682f207238c505b9415aec38fd23e717be3625abe6467209bbb60f9c6a1b7e",
    "file_size_bytes": 2675821,
    "scraped_at": "2026-03-25T16:24:19.726175+00:00",
    "source_page": "https://arcusbio.com/our-science/publications/",
    "page_type": "publications"
  },
  "2025-AACR-PKMYT1-poster-final.pdf": {
    "source_url": "https://arcusbio.com/wp-content/uploads/2025/04/2025-AACR-PKMYT1-poster-final.pdf",
    "title": "Targeting PKMYT1 to Preferentially Kill Tumor Cells that Have CCNE1 Amplifications",
    "date": "2025-04-01",
    "doc_type": "poster",
    "sha256": "f69c1bdc768f16d48895acb376a1595ec5096a6b78b136fe915b4a9891ea35a8",
    "file_size_bytes": 988036,
    "scraped_at": "2026-03-25T16:24:19.808865+00:00",
    "source_page": "https://arcusbio.com/our-science/publications/",
    "page_type": "publications"
  },
  "2025-AACR-ULK-Poster_Final.pdf": {
    "source_url": "https://arcusbio.com/wp-content/uploads/2025/04/2025-AACR-ULK-Poster_Final.pdf",
    "title": "Inhibition of ULK1/2-Mediated Autophagy Augments Antigen Processing and Presentation Promoting Increased Antigen-Specific CD8+ T Cell Cytotoxicity",
    "date": "2025-04-01",
    "doc_type": "poster",
    "sha256": "3217b226daa911f83d4dfae800e0aaf93a4e103b358f0506fb63b90b522695dd",
    "file_size_bytes": 1174139,
    "scraped_at": "2026-03-25T16:24:20.017321+00:00",
    "source_page": "https://arcusbio.com/our-science/publications/",
    "page_type": "publications"
  },
  "2025.04-AACR-AB598-final-V3.pdf": {
    "source_url": "https://arcusbio.com/wp-content/uploads/2025/04/2025.04-AACR-AB598-final-V3.pdf",
    "title": "Inhibition of CD39 by AB598 Enhances the Effects of Chemotherapy and anti-PD-1 Therapy to Promote Myeloid Cell and T Cell anti-Tumor Immunity",
    "date": "2025-04-01",
    "doc_type": "poster",
    "sha256": "4db88b8575aa237a427921feda3477dbf1cd1c6e7d13d9fa19b75faae8033dc3",
    "file_size_bytes": 1717947,
    "scraped_at": "2026-03-25T16:24:20.145215+00:00",
    "source_page": "https://arcusbio.com/our-science/publications/",
    "page_type": "publications"
  },
  "Cost-Effective-Cyanotetralone-Chemical-Development-to-Support-Casdatifan-AB521-DS-Manufacturing-Process-Antoni-poster-032025-final.pdf": {
    "source_url": "https://arcusbio.com/wp-content/uploads/2025/09/Cost-Effective-Cyanotetralone-Chemical-Development-to-Support-Casdatifan-AB521-DS-Manufacturing-Process-Antoni-poster-032025-final.pdf",
    "title": "Cost-Effective Cyanotetralone Chemical Development to Support Casdatifan (AB521) DS Manufacturing Process",
    "date": "2025-09-01",
    "doc_type": "poster",
    "sha256": "db5f0752c58b5e6d186108acfb96d38053645ec574c3afab8027238222e1e947",
    "file_size_bytes": 594092,
    "scraped_at": "2026-03-25T16:24:20.348425+00:00",
    "source_page": "https://arcusbio.com/our-science/publications/",
    "page_type": "publications"
  },
  "Jaen-DRUGGING-ADENOSINE-PATHWAY.pdf": {
    "source_url": "https://arcusbio.com/wp-content/uploads/2025/03/Jaen-DRUGGING-ADENOSINE-PATHWAY.pdf",
    "title": "New Developments in Drugging the Adenosine Pathway",
    "date": "2025-03-01",
    "doc_type": "other",
    "sha256": "c8f78c04e16a1ae8d665c6ee768698dcd5779de6ef5b96a5438d9d7a19db4b38",
    "file_size_bytes": 2706619,
    "scraped_at": "2026-03-25T16:24:20.565497+00:00",
    "source_page": "https://arcusbio.com/our-science/publications/",
    "page_type": "publications"
  },
  "2025-Kinase-Drug-Discovery-Summit.pdf": {
    "source_url": "https://arcusbio.com/wp-content/uploads/2025/03/2025-Kinase-Drug-Discovery-Summit.pdf",
    "title": "AB801 Potently & Selectively Inhibits AXL to Overcome Therapeutic Resistance",
    "date": "2025-03-01",
    "doc_type": "other",
    "sha256": "d7d479057818d2d40d8b11eeee431d2c8a3d119c249c7970a6fd6991b1006b16",
    "file_size_bytes": 5393194,
    "scraped_at": "2026-03-25T16:24:20.893858+00:00",
    "source_page": "https://arcusbio.com/our-science/publications/",
    "page_type": "publications"
  },
  "45072-ARB-24001-21-SITC-2024-DomZim-1461-eP-vF-post.pdf": {
    "source_url": "https://arcusbio.com/wp-content/uploads/2024/11/45072-ARB-24001-21-SITC-2024-DomZim-1461-eP-vF-post.pdf",
    "title": "Randomized Study of Domvanalimab Combined With Zimberelimab in Front-Line, PD-L1\u2013High, Locally Advanced or Metastatic Non-Small Cell Lung Cancer (NSCLC): Results From ARC-10 Part 1",
    "date": "2024-11-01",
    "doc_type": "other",
    "sha256": "6552fbad7d0c2547193ead9fcae1288b75ba22da88e69e1936d53119f0082c38",
    "file_size_bytes": 359752,
    "scraped_at": "2026-03-25T16:24:21.064053+00:00",
    "source_page": "https://arcusbio.com/our-science/publications/",
    "page_type": "publications"
  },
  "45072-ARB-24001-09-SITC-2024-Biomarker-52-eP-v6.pdf": {
    "source_url": "https://arcusbio.com/wp-content/uploads/2024/11/45072-ARB-24001-09-SITC-2024-Biomarker-52-eP-v6.pdf",
    "title": "The Adenosine Receptor Antagonist Etrumadenant Reduces Tumor Adenosine-Regulated NR4A Gene Expression and Increases mCRC Inflammation in Patients From the ARC-9 Trial",
    "date": "2024-11-01",
    "doc_type": "other",
    "sha256": "cb269a7fbfa716a89abe1203365f2a11d0eb55fd9917fc30f564c10d8cb4bb4a",
    "file_size_bytes": 3642533,
    "scraped_at": "2026-03-25T16:24:21.373067+00:00",
    "source_page": "https://arcusbio.com/our-science/publications/",
    "page_type": "publications"
  },
  "2024-TIGIT-SITC-Poster-FINAL-Version-Updated.pdf": {
    "source_url": "https://arcusbio.com/wp-content/uploads/2024/11/2024-TIGIT-SITC-Poster-FINAL-Version-Updated.pdf",
    "title": "TIGIT Blockade By Monoclonal Antibodies Promotes T Cell Activation and Anti-tumor Activity That is Not Dependent on a Functionalized Fc Domain",
    "date": "2024-11-01",
    "doc_type": "poster",
    "sha256": "810ae1fe88d446b783f05dbd91ba56d221450cb6bc39113058ea4b26e4362f86",
    "file_size_bytes": 1211121,
    "scraped_at": "2026-03-25T16:24:21.595978+00:00",
    "source_page": "https://arcusbio.com/our-science/publications/",
    "page_type": "publications"
  },
  "ARB-24001-14.Cas_.Oral_.ENA24.ARC-20.16Oct24_Final_v3-1.pdf": {
    "source_url": "https://arcusbio.com/wp-content/uploads/2024/10/ARB-24001-14.Cas_.Oral_.ENA24.ARC-20.16Oct24_Final_v3-1.pdf",
    "title": "Casdatifan in Patients With Previously Treated Clear Cell Renal Cell Carcinoma and Other Solid Tumors: Preliminary Results From ARC-20, a Phase 1, Open-Label, Dose Escalation and Expansion Study",
    "date": "2024-10-01",
    "doc_type": "other",
    "sha256": "9da1e5050916e536b4407e972eb072a926bbeda65bcc6191bd2afaa9229a453e",
    "file_size_bytes": 898430,
    "scraped_at": "2026-03-25T16:24:21.690768+00:00",
    "source_page": "https://arcusbio.com/our-science/publications/",
    "page_type": "publications"
  },
  "2024-ENA-AB801-poster.pdf": {
    "source_url": "https://arcusbio.com/wp-content/uploads/2024/10/2024-ENA-AB801-poster.pdf",
    "title": "AB801, a Potent and Highly Selective Clinical Stage AXL Inhibitor, Sensitizes Tumors to Standard of Care Therapies",
    "date": "2024-10-01",
    "doc_type": "poster",
    "sha256": "d9aaa47185bcc7c0f7e219847b84d089b82d40c4e8d65298e0f2a20114822c29",
    "file_size_bytes": 1288786,
    "scraped_at": "2026-03-25T16:24:21.924682+00:00",
    "source_page": "https://arcusbio.com/our-science/publications/",
    "page_type": "publications"
  },
  "2024-ENA-Triple-Meeting-HIF2A-v3.pdf": {
    "source_url": "https://arcusbio.com/wp-content/uploads/2024/10/2024-ENA-Triple-Meeting-HIF2A-v3.pdf",
    "title": "AB521 (Casdatifan) Potently and Selectively Inhibits Hypoxia-Inducible Factor 2 Alpha (HIF-2\u03b1) Dependent Pro-Tumorigenic Activity",
    "date": "2024-10-01",
    "doc_type": "other",
    "sha256": "2451cbd1603dd2060dec8e89f47de1aaa9a0e1ee1e95f94d199c1c98fb045daf",
    "file_size_bytes": 1033848,
    "scraped_at": "2026-03-25T16:24:22.138018+00:00",
    "source_page": "https://arcusbio.com/our-science/publications/",
    "page_type": "publications"
  },
  "Ghasemi_ARC-20-PK-PD_ENA-2024_presented.pdf": {
    "source_url": "https://arcusbio.com/wp-content/uploads/2024/10/Ghasemi_ARC-20-PK-PD_ENA-2024_presented.pdf",
    "title": "Clinical Pharmacokinetic/Pharmacodynamic (PK/PD) Relationship for Casdatifan (AB521), a Small Molecule Inhibitor of HIF-2\u03b1, Confirms Best-in-class Potential in Treatment of Renal Cell Carcinoma",
    "date": "2024-10-01",
    "doc_type": "other",
    "sha256": "a41b38d346cc221ec1fc79e2564adebc87246b8113a1b6cd8baf1dff4182f34e",
    "file_size_bytes": 1369233,
    "scraped_at": "2026-03-25T16:24:22.257199+00:00",
    "source_page": "https://arcusbio.com/our-science/publications/",
    "page_type": "publications"
  },
  "45062-ARB-24001-06-AACR-PDAC-2024-ARC-8-Biomarkers-PP-v6.pdf": {
    "source_url": "https://arcusbio.com/wp-content/uploads/2024/09/45062-ARB-24001-06-AACR-PDAC-2024-ARC-8-Biomarkers-PP-v6.pdf",
    "title": "Quemliclustat (CD73 Inhibitor) Reduces Adenosine-Regulated NR4A Gene Expression and Increases mPDAC Inflammation in Patients from the ARC-8 Trial",
    "date": "2024-09-01",
    "doc_type": "poster",
    "sha256": "937dede1272e2d506de1c9e3401e47b53797dce4d54b13776dfba184a0accb6b",
    "file_size_bytes": 935671,
    "scraped_at": "2026-03-25T16:24:22.368039+00:00",
    "source_page": "https://arcusbio.com/our-science/publications/",
    "page_type": "publications"
  },
  "Lawson-ACS-Fall-2024_FINAL.pdf": {
    "source_url": "https://arcusbio.com/wp-content/uploads/2024/08/Lawson-ACS-Fall-2024_FINAL.pdf",
    "title": "Discovery and Characterization of AB521, a Clinical-Stage, Potent, and Selective Hypoxia-Inducible Factor (HIF)-2\u03b1 Inhibitor",
    "date": "2024-08-01",
    "doc_type": "other",
    "sha256": "1a4afb763c3f6984b354b482f9384b9ff2c56b95eec696f8ab9be9fea38fee91",
    "file_size_bytes": 4245320,
    "scraped_at": "2026-03-25T16:24:22.647544+00:00",
    "source_page": "https://arcusbio.com/our-science/publications/",
    "page_type": "publications"
  },
  "Cas_Poster_KCRS2024_2July2024_for-release.pdf": {
    "source_url": "https://arcusbio.com/wp-content/uploads/2024/07/Cas_Poster_KCRS2024_2July2024_for-release.pdf",
    "title": "Clinical Pharmacokinetic/Pharmacodynamic (PK/PD) Relationship Confirms Best-in-class Potential of Casdatifan (AB521), a Small Molecule Inhibitor of HIF-2\u03b1 Being Developed in Renal Cancer",
    "date": "2024-07-01",
    "doc_type": "poster",
    "sha256": "e4b54743836a0987e12d05579de65e854350e2befc9983510fdfb8cbf41f0440",
    "file_size_bytes": 1251698,
    "scraped_at": "2026-03-25T16:24:22.763358+00:00",
    "source_page": "https://arcusbio.com/our-science/publications/",
    "page_type": "publications"
  },
  "Kim_MORPHEUS_PDAC_AACR-2024_poster_FINAL_27Mar2024.pdf": {
    "source_url": "https://arcusbio.com/wp-content/uploads/2024/04/Kim_MORPHEUS_PDAC_AACR-2024_poster_FINAL_27Mar2024.pdf",
    "title": "Phase Ib/II, global, open-label, randomized evaluation of atezolizumab (atezo) + etrumadenant (etruma) + chemotherapy (chemo) vs chemo alone in MORPHEUS-PDAC",
    "date": "2024-04-01",
    "doc_type": "poster",
    "sha256": "dffa26bc6e40ab0fbb3f60f0d349567516a53719ded6962790097ab6362bf10e",
    "file_size_bytes": 306429,
    "scraped_at": "2026-03-25T16:24:22.838411+00:00",
    "source_page": "https://arcusbio.com/our-science/publications/",
    "page_type": "publications"
  },
  "2024.04.03-AACR-Poster-Cbl.pdf": {
    "source_url": "https://arcusbio.com/wp-content/uploads/2024/04/2024.04.03-AACR-Poster-Cbl.pdf",
    "title": "Cbl Inhibition Increases the Response of Cytotoxic T Cells to Sub-Optimal Stimulation and Drives Enhanced Anti-Tumor Responses Alone or in Combination with PD-1 Blockade",
    "date": "2024-04-01",
    "doc_type": "poster",
    "sha256": "1c4d688c30597234aa20831b453ca0730c0b3d63a58328790db72d970a792e17",
    "file_size_bytes": 845622,
    "scraped_at": "2026-03-25T16:24:22.937661+00:00",
    "source_page": "https://arcusbio.com/our-science/publications/",
    "page_type": "publications"
  },
  "2024-AACR-ULK-poster_2.pdf": {
    "source_url": "https://arcusbio.com/wp-content/uploads/2024/04/2024-AACR-ULK-poster_2.pdf",
    "title": "Inhibition of ULK1/2-Mediated Autophagy Augments Antigen Processing and Presentation in STK11-mutant NSCLC",
    "date": "2024-04-01",
    "doc_type": "poster",
    "sha256": "7dc01253e186e8fcad7f6be86bbb02fe2fa035863bf927f698e1338d6673781b",
    "file_size_bytes": 2889870,
    "scraped_at": "2026-03-25T16:24:23.175629+00:00",
    "source_page": "https://arcusbio.com/our-science/publications/",
    "page_type": "publications"
  },
  "2024-AACR-AB598-poster.pdf": {
    "source_url": "https://arcusbio.com/wp-content/uploads/2024/04/2024-AACR-AB598-poster.pdf",
    "title": "Inhibition of CD39 by AB598 Increases Extracellular ATP Resulting in Activation of Myeloid Cells and T Cells to Enhance Anti-Tumor Immunity",
    "date": "2024-04-01",
    "doc_type": "poster",
    "sha256": "3c04eeed0da71f6a15fed6af17ab46fb543925445e167462a6896decc9f15502",
    "file_size_bytes": 729587,
    "scraped_at": "2026-03-25T16:24:23.357122+00:00",
    "source_page": "https://arcusbio.com/our-science/publications/",
    "page_type": "publications"
  },
  "etruma_ara_poster_ascpt2024_final_v3.pdf": {
    "source_url": "https://arcusbio.com/wp-content/uploads/2024/03/etruma_ara_poster_ascpt2024_final_v3.pdf",
    "title": "Food and Co-administration of Acid Reducing Agents (ARAs) Have No Clinically Significant Effect on the Pharmacokinetics of Etrumadenant, a Novel Dual Adenosine Receptor Antagonist \u2013Population Pharmacokinetic (PopPK) and Physiologically-Based (PBPK) Modeling Exploration",
    "date": "2024-03-01",
    "doc_type": "poster",
    "sha256": "184464a38d0ef615e1f411fc090ee8634f566848055714f9c34dee3c7dd759c6",
    "file_size_bytes": 961748,
    "scraped_at": "2026-03-25T16:24:23.554660+00:00",
    "source_page": "https://arcusbio.com/our-science/publications/",
    "page_type": "publications"
  },
  "AB521-popPK-ASCPT-2024_Poster_20240305_final.pdf": {
    "source_url": "https://arcusbio.com/wp-content/uploads/2024/03/AB521-popPK-ASCPT-2024_Poster_20240305_final.pdf",
    "title": "Population Pharmacokinetic (PopPK) Model of AB521 (Casdatifan), a Small Molecule Inhibitor of HIF-2\u03b1, in Healthy Participants",
    "date": "2024-03-01",
    "doc_type": "poster",
    "sha256": "21735bd08ad0f9a3ef29c04817cab050dedea1d45faa5b90192a11af7541ba0b",
    "file_size_bytes": 872842,
    "scraped_at": "2026-03-25T16:24:23.692675+00:00",
    "source_page": "https://arcusbio.com/our-science/publications/",
    "page_type": "publications"
  },
  "ARC-19-ASCPT_poster_final-v2.pdf": {
    "source_url": "https://arcusbio.com/wp-content/uploads/2024/03/ARC-19-ASCPT_poster_final-v2.pdf",
    "title": "Multiple Elimination Pathways are Responsible for the Elimination of Etrumadenant after Oral Administration of [14C]-Etrumadenant to Humans",
    "date": "2024-03-01",
    "doc_type": "poster",
    "sha256": "6a3d1c58e560f731372cc5db0e65e40f3f3ed19a990f70d79502ec3c7fc2e949",
    "file_size_bytes": 733908,
    "scraped_at": "2026-03-25T16:24:23.889793+00:00",
    "source_page": "https://arcusbio.com/our-science/publications/",
    "page_type": "publications"
  },
  "20240317-Keystone-I-O-TIGIT-Oral-Presentation.pdf": {
    "source_url": "https://arcusbio.com/wp-content/uploads/2024/03/20240317-Keystone-I-O-TIGIT-Oral-Presentation.pdf",
    "title": "Fc-silent Anti-TIGIT Antibodies Offer Best-in-Class Potential By Potentiating Robust CD8+T Cell-Mediated Anti-tumor Immunity Without Peripheral Regulatory T Cell Depletion",
    "date": "2024-03-01",
    "doc_type": "other",
    "sha256": "b0918cc71ee736bd64aeb616da504c3759fdc0d955db1868bdbb7a7e090fc56d",
    "file_size_bytes": 5369908,
    "scraped_at": "2026-03-25T16:24:24.093572+00:00",
    "source_page": "https://arcusbio.com/our-science/publications/",
    "page_type": "publications"
  },
  "2024.03_poster_Artur.pdf": {
    "source_url": "https://arcusbio.com/wp-content/uploads/2024/03/2024.03_poster_Artur.pdf",
    "title": "Discovery and Optimization of HIF-2\u03b1 Inhibitors",
    "date": "2024-03-01",
    "doc_type": "poster",
    "sha256": "7be0dd40f57f4ae6af108329ee7b2375193e2193b613ca5e9dc1c2a2c547eaa3",
    "file_size_bytes": 1390848,
    "scraped_at": "2026-03-25T16:24:24.221770+00:00",
    "source_page": "https://arcusbio.com/our-science/publications/",
    "page_type": "publications"
  },
  "HIF-2a_G323E_Draft_CM01232024.pdf": {
    "source_url": "https://arcusbio.com/wp-content/uploads/2024/01/HIF-2a_G323E_Draft_CM01232024.pdf",
    "title": "Development of Cell-based Assays for the Identification and Characterization of Inhibitors of Mutant G323E Hypoxia Inducible Factor-2\u03b1 (HIF-2\u03b1)",
    "date": "2024-01-01",
    "doc_type": "other",
    "sha256": "d4c193dcbd89e6d37c6e8d975e9fb7a97561ea785e8e92051d1a62fc8932b9eb",
    "file_size_bytes": 1177708,
    "scraped_at": "2026-03-25T16:24:24.391866+00:00",
    "source_page": "https://arcusbio.com/our-science/publications/",
    "page_type": "publications"
  },
  "FLT3-poster-240119.pdf": {
    "source_url": "https://arcusbio.com/wp-content/uploads/2024/01/FLT3-poster-240119.pdf",
    "title": "A novel cell-based assay to identify the FLT3 kinase construct used in enzyme assays that best represents the activity of cellular FLT3",
    "date": "2024-01-01",
    "doc_type": "poster",
    "sha256": "4b4ed2a6884dd2fa498035df96a225e2fcc341478ef6820d82e612122a9a61c3",
    "file_size_bytes": 541450,
    "scraped_at": "2026-03-25T16:24:24.472660+00:00",
    "source_page": "https://arcusbio.com/our-science/publications/",
    "page_type": "publications"
  },
  "AXL_MidwinterPoster_2024.pdf": {
    "source_url": "https://arcusbio.com/wp-content/uploads/2024/01/AXL_MidwinterPoster_2024.pdf",
    "title": "Inhibition of AXL Signaling with AB801 Augments Anti-Tumor Immune Responses",
    "date": "2024-01-01",
    "doc_type": "poster",
    "sha256": "62e2277bd5f9d5f37217a811f96d72385bfac8dcc50c189659b7189aebd67210",
    "file_size_bytes": 1168343,
    "scraped_at": "2026-03-25T16:24:24.623350+00:00",
    "source_page": "https://arcusbio.com/our-science/publications/",
    "page_type": "publications"
  },
  "ARC-8-ASCO-GI-2024-Poster_Final-Draft_8Jan2024.pdf": {
    "source_url": "https://arcusbio.com/wp-content/uploads/2024/01/ARC-8-ASCO-GI-2024-Poster_Final-Draft_8Jan2024.pdf",
    "title": "ARC\u20118: Phase 1/1b Randomized Study of Quemliclustat + Gemcitabine / Nab\u2011Paclitaxel \u00b1 Zimberelimab in Patients With Treatment\u2011Naive Metastatic Pancreatic Adenocarcinoma",
    "date": "2024-01-01",
    "doc_type": "poster",
    "sha256": "d40d4ca5e5533e4c37def1ce3261ce9c387d23e405aca8387d47d115e64d1871",
    "file_size_bytes": 833566,
    "scraped_at": "2026-03-25T16:24:24.829701+00:00",
    "source_page": "https://arcusbio.com/our-science/publications/",
    "page_type": "publications"
  },
  "20231024-SITC-CD39-FINAL.pdf": {
    "source_url": "https://arcusbio.com/wp-content/uploads/2023/10/20231024-SITC-CD39-FINAL.pdf",
    "title": "AB598, a CD39 Inhibitory Antibody, Promotes Immune-Mediated Tumor Control",
    "date": "2023-10-01",
    "doc_type": "other",
    "sha256": "acbeb09c80715f57676273580e6662fe477cf5b70b1c53325dd44fcdc6f26ed5",
    "file_size_bytes": 657067,
    "scraped_at": "2026-03-25T16:24:24.914295+00:00",
    "source_page": "https://arcusbio.com/our-science/publications/",
    "page_type": "publications"
  },
  "2023-SITC-Arcus-DGK-v4.pdf": {
    "source_url": "https://arcusbio.com/wp-content/uploads/2023/10/2023-SITC-Arcus-DGK-v4.pdf",
    "title": "Dual Inhibition DGK\u03b1and DGK\u03b6 Increases T Cell and NK Cell Activity",
    "date": "2023-10-01",
    "doc_type": "other",
    "sha256": "a8fe882846164b70cc20e53fdcba2b2e435ea73dd891dac764d1b419ad268e33",
    "file_size_bytes": 1744754,
    "scraped_at": "2026-03-25T16:24:25.071757+00:00",
    "source_page": "https://arcusbio.com/our-science/publications/",
    "page_type": "publications"
  },
  "2023-SITC-AXL.pdf": {
    "source_url": "https://arcusbio.com/wp-content/uploads/2023/10/2023-SITC-AXL.pdf",
    "title": "Inhibition of AXL Signaling with AB801 Augments Anti-Tumor Immune Responses",
    "date": "2023-10-01",
    "doc_type": "other",
    "sha256": "df11b17fd07509db7c48ec4d31735fd077e4a3424297a8aec22997a9c0458f9e",
    "file_size_bytes": 1201391,
    "scraped_at": "2026-03-25T16:24:25.272275+00:00",
    "source_page": "https://arcusbio.com/our-science/publications/",
    "page_type": "publications"
  },
  "2023-SITC-TIGIT.pdf": {
    "source_url": "https://arcusbio.com/wp-content/uploads/2023/10/2023-SITC-TIGIT.pdf",
    "title": "Fc-silent Anti-TIGIT Antibodies Potentiate Anti-tumor Immunity Without Depleting Regulatory T Cells",
    "date": "2023-10-01",
    "doc_type": "other",
    "sha256": "0c4a42761a03111552c98a488f5e4a0d36fb05b449463f81cbb187292a9239ad",
    "file_size_bytes": 3535907,
    "scraped_at": "2026-03-25T16:24:25.490434+00:00",
    "source_page": "https://arcusbio.com/our-science/publications/",
    "page_type": "publications"
  },
  "2023-SITC-etruma-FINAL-ver2.pdf": {
    "source_url": "https://arcusbio.com/wp-content/uploads/2023/10/2023-SITC-etruma-FINAL-ver2.pdf",
    "title": "Combined Administration of the Dual A2aR/A2bR Antagonist Etrumadenant with a Reduced Chemotherapy Regimen Leads to Enhanced Tumor Efficacy and Survival",
    "date": "2023-10-01",
    "doc_type": "other",
    "sha256": "b2cf2c81124a5e44f238b588ad87ef3c00a7ba145967e42b396a1a7b76672b71",
    "file_size_bytes": 1606783,
    "scraped_at": "2026-03-25T16:24:25.612854+00:00",
    "source_page": "https://arcusbio.com/our-science/publications/",
    "page_type": "publications"
  },
  "2023-SITC-STUB1.pdf": {
    "source_url": "https://arcusbio.com/wp-content/uploads/2023/10/2023-SITC-STUB1.pdf",
    "title": "STUB1 regulates IFNGR1 expression and IFNG sensitivity in human tumor cell lines",
    "date": "2023-10-01",
    "doc_type": "other",
    "sha256": "1eceafaae05a0d6fa465f21a7fa829c2ff7e08c5de3e65395561a1a697a63a7f",
    "file_size_bytes": 996517,
    "scraped_at": "2026-03-25T16:24:25.790706+00:00",
    "source_page": "https://arcusbio.com/our-science/publications/",
    "page_type": "publications"
  },
  "20230929-ImmunoUS_.pdf": {
    "source_url": "https://arcusbio.com/wp-content/uploads/2023/10/20230929-ImmunoUS_.pdf",
    "title": "Inhibition of CD39 to Promote Anti-Tumor Immune Responses",
    "date": "2023-10-01",
    "doc_type": "other",
    "sha256": "f80041ba60c184ea8b9054cb4c9c86baafaae5f644335c2be64094cc8f6dcecf",
    "file_size_bytes": 4091634,
    "scraped_at": "2026-03-25T16:24:25.945604+00:00",
    "source_page": "https://arcusbio.com/our-science/publications/",
    "page_type": "publications"
  },
  "2023.10-AACR-HIF2A-G3223E-Poster-v2.pdf": {
    "source_url": "https://arcusbio.com/wp-content/uploads/2023/10/2023.10-AACR-HIF2A-G3223E-Poster-v2.pdf",
    "title": "Partially Open Conformation of The G323E Mutated HIF-2\u03b1 PASB Domain Captured By X-ray Crystallography",
    "date": "2023-10-01",
    "doc_type": "poster",
    "sha256": "e3b0e0d433875f3256281f9465f30857bad0f53447370082972034a3526bc29e",
    "file_size_bytes": 2130164,
    "scraped_at": "2026-03-25T16:24:26.057688+00:00",
    "source_page": "https://arcusbio.com/our-science/publications/",
    "page_type": "publications"
  },
  "Discovery-on-Target-Boston-Sept-2023_FINAL.pdf": {
    "source_url": "https://arcusbio.com/wp-content/uploads/2023/10/Discovery-on-Target-Boston-Sept-2023_FINAL.pdf",
    "title": "Discovery and Optimization of HIF-2\u03b1 Inhibitors",
    "date": "2023-10-01",
    "doc_type": "other",
    "sha256": "f2072b07b6edc24e61c4a720b44b236e056a4d50a4bc9ab94327c9cc9fce6911",
    "file_size_bytes": 2728840,
    "scraped_at": "2026-03-25T16:24:26.201164+00:00",
    "source_page": "https://arcusbio.com/our-science/publications/",
    "page_type": "publications"
  },
  "20230921-PBSS-Advances-in-Cancer-Therapeutics-Symposium-TIGIT.pdf": {
    "source_url": "https://arcusbio.com/wp-content/uploads/2023/10/20230921-PBSS-Advances-in-Cancer-Therapeutics-Symposium-TIGIT.pdf",
    "title": "F-c Silent anti-TIGIT Antibodies Potentiate Anti-Tumor Immunity Without Depleting Regulatory T Cells",
    "date": "2023-10-01",
    "doc_type": "other",
    "sha256": "3ef9ff61bca183ed5595fa4ff82992b562d349dd6d2e8b70d2a36b7948f3cefc",
    "file_size_bytes": 4755567,
    "scraped_at": "2026-03-25T16:24:26.462089+00:00",
    "source_page": "https://arcusbio.com/our-science/publications/",
    "page_type": "publications"
  },
  "2023-AACR-Kidney-Special-Conference-AB521-Poster.pdf": {
    "source_url": "https://arcusbio.com/wp-content/uploads/2023/06/2023-AACR-Kidney-Special-Conference-AB521-Poster.pdf",
    "title": "Targeting Hypoxia Inducible Factor (HIF)-2\u03b1 With AB521,\u00a0a Novel and Potent Small Molecule HIF-2\u03b1 Inhibitor, for the Treatment of Clear Cell Renal Cell Carcinoma",
    "date": "2023-06-01",
    "doc_type": "poster",
    "sha256": "8478deeab2ad091d74b0507953b2eecbd39f2cf1fd07bf8da3297e6661c817e1",
    "file_size_bytes": 1047551,
    "scraped_at": "2026-03-25T16:24:26.596250+00:00",
    "source_page": "https://arcusbio.com/our-science/publications/",
    "page_type": "publications"
  },
  "2023.04.10-AACR-AB598-PD-Poster_FINAL.pdf": {
    "source_url": "https://arcusbio.com/wp-content/uploads/2023/04/2023.04.10-AACR-AB598-PD-Poster_FINAL.pdf",
    "title": "Characterization of AB598, a Therapeutic Anti-Human CD39 Antibody for the Treatment of Cancer",
    "date": "2023-04-01",
    "doc_type": "poster",
    "sha256": "1ffd4ef92bc882504b6cf652e7af9b5f3163fe365c402050f117d7c2524733af",
    "file_size_bytes": 2477167,
    "scraped_at": "2026-03-25T16:24:26.845631+00:00",
    "source_page": "https://arcusbio.com/our-science/publications/",
    "page_type": "publications"
  },
  "2023-AACR-AXL-Poster-final.pdf": {
    "source_url": "https://arcusbio.com/wp-content/uploads/2023/04/2023-AACR-AXL-Poster-final.pdf",
    "title": "AB801 is a Highly Potent and Selective AXL Kinase Inhibitor that Demonstrates Significant Anti-Tumor Activity",
    "date": "2023-04-01",
    "doc_type": "poster",
    "sha256": "dde99e4825627b435bc7f2f0c9056d2f396eaf8825c5e8988c97064622372d40",
    "file_size_bytes": 1432297,
    "scraped_at": "2026-03-25T16:24:26.941161+00:00",
    "source_page": "https://arcusbio.com/our-science/publications/",
    "page_type": "publications"
  },
  "2023.03-ACS-AXL-Inhibitors-poster_Approved-Final-1.pdf": {
    "source_url": "https://arcusbio.com/wp-content/uploads/2023/03/2023.03-ACS-AXL-Inhibitors-poster_Approved-Final-1.pdf",
    "title": "Discovery and characterization of orally bioavailable, potent, and selective small-molecule AXL kinase inhibitors for cancer therapy",
    "date": "2023-03-01",
    "doc_type": "poster",
    "sha256": "d9a62a2baa713b25d73555cf40de68e187d2e389669014960fa6f6d16b030f05",
    "file_size_bytes": 623362,
    "scraped_at": "2026-03-25T16:24:27.032106+00:00",
    "source_page": "https://arcusbio.com/our-science/publications/",
    "page_type": "publications"
  },
  "2023.03-Spring-ACS-AXL-Poster_FINAL.pdf": {
    "source_url": "https://arcusbio.com/wp-content/uploads/2023/04/2023.03-Spring-ACS-AXL-Poster_FINAL.pdf",
    "title": "Discovery and characterization of potent and selective AXL receptor tyrosine kinase inhibitors",
    "date": "2023-04-01",
    "doc_type": "poster",
    "sha256": "d3b07114dded8a6cdd71a39721489e3e11ede1be288e2d2ae3efefb41a81b398",
    "file_size_bytes": 898039,
    "scraped_at": "2026-03-25T16:24:27.176146+00:00",
    "source_page": "https://arcusbio.com/our-science/publications/",
    "page_type": "publications"
  },
  "ASCPT_DOM_2023_final.pdf": {
    "source_url": "https://arcusbio.com/wp-content/uploads/2023/03/ASCPT_DOM_2023_final.pdf",
    "title": "Use of a population pharmacokinetic modelling and simulation approach to identify flat doses of domvanalimab in phase 3 studies",
    "date": "2023-03-01",
    "doc_type": "other",
    "sha256": "71c54d7f8fe2820ac4da6d9b4786fa4daf59b75c37a66af9b815219320815a93",
    "file_size_bytes": 6887066,
    "scraped_at": "2026-03-25T16:24:27.468887+00:00",
    "source_page": "https://arcusbio.com/our-science/publications/",
    "page_type": "publications"
  },
  "150203310_ASCPT2023_Poster_L2b.pdf": {
    "source_url": "https://arcusbio.com/wp-content/uploads/2023/03/150203310_ASCPT2023_Poster_L2b.pdf",
    "title": "Limited drug interaction supported by a clinical drug interaction study and physiologically based pharmacokinetic modeling of etrumadenant (AB928), a novel dual adenosine receptor antagonist, under coadministration with a strong CYP3A4 and p-glycoprotein inhibitor (itraconazole) in healthy participants",
    "date": "2023-03-01",
    "doc_type": "poster",
    "sha256": "ffac3ddd9228e8fb183ea78fa4abd49f7825247db0ffc892178ddc0bdeb1ad37",
    "file_size_bytes": 1325152,
    "scraped_at": "2026-03-25T16:24:27.568076+00:00",
    "source_page": "https://arcusbio.com/our-science/publications/",
    "page_type": "publications"
  },
  "2023-ESMO-TAT-HIF2a-AB521-HCC-poster-FINAL.pdf": {
    "source_url": "https://arcusbio.com/wp-content/uploads/2023/03/2023-ESMO-TAT-HIF2a-AB521-HCC-poster-FINAL.pdf",
    "title": "Inhibition of HIF-2\u03b1-dependent transcription with small molecule inhibitors may provide therapeutic benefit beyond renal cell carcinoma",
    "date": "2023-03-01",
    "doc_type": "poster",
    "sha256": "b4b1daa42b877e688845a78b1741c10ae7d77d7414c4e76b22233e26aca39f37",
    "file_size_bytes": 2227701,
    "scraped_at": "2026-03-25T16:24:27.676527+00:00",
    "source_page": "https://arcusbio.com/our-science/publications/",
    "page_type": "publications"
  },
  "20230117-CD39-Midwinter-Immunol-FINAL-corr-year.pdf": {
    "source_url": "https://arcusbio.com/wp-content/uploads/2023/03/20230117-CD39-Midwinter-Immunol-FINAL-corr-year.pdf",
    "title": "Rationale for the combination of AB598, a CD39 blocking antibody, and chemotherapy for the treatment of solid tumors",
    "date": "2023-03-01",
    "doc_type": "other",
    "sha256": "1f39a1ebd9195efe216242e61b742719d1a23ac43381765f1326887b88784bc0",
    "file_size_bytes": 1012071,
    "scraped_at": "2026-03-25T16:24:27.898703+00:00",
    "source_page": "https://arcusbio.com/our-science/publications/",
    "page_type": "publications"
  },
  "2022.10.25-etruma-SITC-2022-Poster-Final.pdf": {
    "source_url": "https://arcusbio.com/wp-content/uploads/2022/11/2022.10.25-etruma-SITC-2022-Poster-Final.pdf",
    "title": "The anti-tumor efficacy of immunogenic chemotherapy is enhanced by the dual A2aR/A2bR antagonist etrumadenant, relieving the necessity for a full chemotherapy regimen.",
    "date": "2022-11-01",
    "doc_type": "poster",
    "sha256": "6bcd20df19609025c15c88bee8461c74aa86c0261f0ffcdf75b4cad0014c69db",
    "file_size_bytes": 1148093,
    "scraped_at": "2026-03-25T16:24:27.998239+00:00",
    "source_page": "https://arcusbio.com/our-science/publications/",
    "page_type": "publications"
  },
  "20221010-SITC_FINAL.pdf": {
    "source_url": "https://arcusbio.com/wp-content/uploads/2022/11/20221010-SITC_FINAL.pdf",
    "title": "AB598, a therapeutic anti-human CD39 antibody, binds and inhibits CD39 enzymatic activity in vivo to promote anti-tumor immunity",
    "date": "2022-11-01",
    "doc_type": "other",
    "sha256": "9ef8e55d1003b306c334a6a444d7a5a4702faa7c4a1a31417840ef7a3cb4a262",
    "file_size_bytes": 1408481,
    "scraped_at": "2026-03-25T16:24:28.102767+00:00",
    "source_page": "https://arcusbio.com/our-science/publications/",
    "page_type": "publications"
  },
  "HPK1-SITC-2022-110222.pdf": {
    "source_url": "https://arcusbio.com/wp-content/uploads/2022/11/HPK1-SITC-2022-110222.pdf",
    "title": "HPK1 inhibition relieves suppression downstream of TCR activation to drive enhanced cytokine production, an effect that is further enhanced by immune checkpoint blockade",
    "date": "2022-11-01",
    "doc_type": "other",
    "sha256": "557a33526c588eceb9f7996ce93aa87f2bc4aacfb38b2c14eae5a20759ef3f14",
    "file_size_bytes": 1019052,
    "scraped_at": "2026-03-25T16:24:28.206540+00:00",
    "source_page": "https://arcusbio.com/our-science/publications/",
    "page_type": "publications"
  },
  "2022-ENA-AXL-Poster_Biology_final.pdf": {
    "source_url": "https://arcusbio.com/wp-content/uploads/2022/10/2022-ENA-AXL-Poster_Biology_final.pdf",
    "title": "AB801 is a potent and selective AXL inhibitor that demonstrates significant anti-tumor activity in combination with standard of care therapeutics",
    "date": "2022-10-01",
    "doc_type": "poster",
    "sha256": "f9cb91d70c46a18d99ddf41c76cf9a2e445550205319e51413e8a8b7214827ff",
    "file_size_bytes": 1749810,
    "scraped_at": "2026-03-25T16:24:28.432084+00:00",
    "source_page": "https://arcusbio.com/our-science/publications/",
    "page_type": "publications"
  },
  "2022-ENA-AB801-Characterization.pdf": {
    "source_url": "https://arcusbio.com/wp-content/uploads/2022/10/2022-ENA-AB801-Characterization.pdf",
    "title": "Discovery and characterization of potent and selective AXL receptor tyrosine kinase inhibitor AB801",
    "date": "2022-10-01",
    "doc_type": "other",
    "sha256": "1f6d3429b30e4105946b665a4a84a9ce9680d5bcddb877fcb00e897eb81007da",
    "file_size_bytes": 571691,
    "scraped_at": "2026-03-25T16:24:28.518139+00:00",
    "source_page": "https://arcusbio.com/our-science/publications/",
    "page_type": "publications"
  },
  "PB048_Liao-et-al_AB521_final.pdf": {
    "source_url": "https://arcusbio.com/wp-content/uploads/2022/10/PB048_Liao-et-al_AB521_final.pdf",
    "title": "HIF-2\u03b1 inhibitor AB521 modulates erythropoietin levels in healthy volunteers following a single oral dose",
    "date": "2022-10-01",
    "doc_type": "other",
    "sha256": "2f6d312aeadffbe0191579da51f10fd984ded166b24748045fdac8b8e09f99d7",
    "file_size_bytes": 1087134,
    "scraped_at": "2026-03-25T16:24:28.642046+00:00",
    "source_page": "https://arcusbio.com/our-science/publications/",
    "page_type": "publications"
  },
  "20221010-AACR-IO_FINAL.pdf": {
    "source_url": "https://arcusbio.com/wp-content/uploads/2022/10/20221010-AACR-IO_FINAL.pdf",
    "title": "AB598, a therapeutic anti-CD39 antibody, elevates ATP and increases immunogenicity in the tumor microenvironment",
    "date": "2022-10-01",
    "doc_type": "poster",
    "sha256": "9fbd90f8dbcb821006fdc75e0f76b7bde9687e5476eab8c7327310eac3995b6c",
    "file_size_bytes": 1604692,
    "scraped_at": "2026-03-25T16:24:28.767525+00:00",
    "source_page": "https://arcusbio.com/our-science/publications/",
    "page_type": "publications"
  },
  "AACR-TII-HPK1-final-poster.pdf": {
    "source_url": "https://arcusbio.com/wp-content/uploads/2022/10/AACR-TII-HPK1-final-poster.pdf",
    "title": "HPK1 inhibition enhances T cell activation and relieves the immunosuppressive effects of extracellular substances found in the tumor microenvironment",
    "date": "2022-10-01",
    "doc_type": "poster",
    "sha256": "027f3d330eb6e911d101a932a8e36a5345c48d0642e1afbd757167297dd8ca1d",
    "file_size_bytes": 574729,
    "scraped_at": "2026-03-25T16:24:28.923310+00:00",
    "source_page": "https://arcusbio.com/our-science/publications/",
    "page_type": "publications"
  },
  "2022-06-14-FOCiS-TIGIT-Poster.pdf": {
    "source_url": "https://arcusbio.com/wp-content/uploads/2022/06/2022-06-14-FOCiS-TIGIT-Poster.pdf",
    "title": "Anti-TIGIT Antibodies Promote Immune Activation in Combination with Immunotherapeutic Agents",
    "date": "2022-06-01",
    "doc_type": "poster",
    "sha256": "4c529362f0bdad89ed158e401d740c214146430065c2e09856f58ec37142c140",
    "file_size_bytes": 4495856,
    "scraped_at": "2026-03-25T16:24:29.070933+00:00",
    "source_page": "https://arcusbio.com/our-science/publications/",
    "page_type": "publications"
  },
  "2022-06-14-FOCiS-TIGIT-Oral-presentation.pdf": {
    "source_url": "https://arcusbio.com/wp-content/uploads/2022/06/2022-06-14-FOCiS-TIGIT-Oral-presentation.pdf",
    "title": "Inhibiting TIGIT to Promote Anti-Tumor Immunity",
    "date": "2022-06-01",
    "doc_type": "other",
    "sha256": "49dfc21db0938be58c0d1a6fab92be73a3864e66cd155e8f9675d0d3932b0a90",
    "file_size_bytes": 7026164,
    "scraped_at": "2026-03-25T16:24:29.276043+00:00",
    "source_page": "https://arcusbio.com/our-science/publications/",
    "page_type": "publications"
  },
  "2022-AAI-TIGIT-Poster.pdf": {
    "source_url": "https://arcusbio.com/wp-content/uploads/2022/05/2022-AAI-TIGIT-Poster.pdf",
    "title": "Anti-TIGIT Antibodies Promote Immune Activation Relevant to Targeting Stem-like and Tumor-specific T Cells in Combination With Anti-PD-1",
    "date": "2022-05-01",
    "doc_type": "poster",
    "sha256": "b4297558db1edf0decaea0a79dc50cccd13fe0972478ed65775b9d45eb9cdb96",
    "file_size_bytes": 1285160,
    "scraped_at": "2026-03-25T16:24:29.457848+00:00",
    "source_page": "https://arcusbio.com/our-science/publications/",
    "page_type": "publications"
  },
  "2022-IKCS-Europe-HIF2a-poster-FINAL.pdf": {
    "source_url": "https://arcusbio.com/wp-content/uploads/2022/04/2022-IKCS-Europe-HIF2a-poster-FINAL.pdf",
    "title": "AB521 is a Novel and Potent Clinical-Stage HIF-2a Inhibitor for the Treatment of Renal Cell Carcinoma",
    "date": "2022-04-01",
    "doc_type": "poster",
    "sha256": "151e78cd3568625f0ae87a0df54e68be45368e9a1aece4de4a4f6527f0934dee",
    "file_size_bytes": 1260349,
    "scraped_at": "2026-03-25T16:24:29.618868+00:00",
    "source_page": "https://arcusbio.com/our-science/publications/",
    "page_type": "publications"
  },
  "Piovesan-2022-Mol-Cancer-Ther-Targeting-CD73-with-Quemliclustat.pdf": {
    "source_url": "https://arcusbio.com/wp-content/uploads/2022/06/Piovesan-2022-Mol-Cancer-Ther-Targeting-CD73-with-Quemliclustat.pdf",
    "title": "Targeting CD73 with AB680 (Quemliclustat), a Novel and Potent Small-Molecule CD73 Inhibitor, Restores Immune Functionality and Facilitates Antitumor Immunity",
    "date": "2022-06-01",
    "doc_type": "other",
    "sha256": "f5dbc78b9082b4e509a472d812beed8b5156fd1478fe45a455926b464e9827ae",
    "file_size_bytes": 1515438,
    "scraped_at": "2026-03-25T16:24:29.728887+00:00",
    "source_page": "https://arcusbio.com/our-science/publications/",
    "page_type": "publications"
  },
  "20220329-AACR-CD39-Poster-FINAL-printed.pdf": {
    "source_url": "https://arcusbio.com/wp-content/uploads/2022/04/20220329-AACR-CD39-Poster-FINAL-printed.pdf",
    "title": "Inhibition of CD39 Results in Elevated ATP and Activation of Myeloid Cells to Promote Anti-Tumor Immunity",
    "date": "2022-04-01",
    "doc_type": "poster",
    "sha256": "8e7e3caa19380e35544b4dd4856de411b0f2d6231752dc5e5116c45313188dd3",
    "file_size_bytes": 908297,
    "scraped_at": "2026-03-25T16:24:29.865631+00:00",
    "source_page": "https://arcusbio.com/our-science/publications/",
    "page_type": "publications"
  },
  "2022.03.17-AACR-Poster-HPK1-FINAL.pdf": {
    "source_url": "https://arcusbio.com/wp-content/uploads/2022/03/2022.03.17-AACR-Poster-HPK1-FINAL.pdf",
    "title": "HPK1 inhibition enhances T cell activation and relieves the immunosuppressive phenotype of inhibitory signals found in the tumor microenvironment",
    "date": "2022-03-01",
    "doc_type": "poster",
    "sha256": "abc2fc257f60ba17f49c598f158a8bfc5fecda220197996085e5b47b7c2dfe00",
    "file_size_bytes": 953568,
    "scraped_at": "2026-03-25T16:24:30.041485+00:00",
    "source_page": "https://arcusbio.com/our-science/publications/",
    "page_type": "publications"
  },
  "2022.02.21-AACR-Poster-etruma-FINAL.pdf": {
    "source_url": "https://arcusbio.com/wp-content/uploads/2022/03/2022.02.21-AACR-Poster-etruma-FINAL.pdf",
    "title": "Dual A2aR/A2bR antagonism with etrumadenant (AB928) eliminates the suppressive effects of adenosine on immune and cancer cells in the tumor microenvironment",
    "date": "2022-03-01",
    "doc_type": "poster",
    "sha256": "a5908a247c49443590dc16b4d8ad2d4b93aa7af293f1eefdc7b31898287f09e9",
    "file_size_bytes": 4159691,
    "scraped_at": "2026-03-25T16:24:30.262668+00:00",
    "source_page": "https://arcusbio.com/our-science/publications/",
    "page_type": "publications"
  },
  "AB680-PKPD-ASCPT-2022_Poster3.0_final-approval_QRcode.pdf": {
    "source_url": "https://arcusbio.com/wp-content/uploads/2022/03/AB680-PKPD-ASCPT-2022_Poster3.0_final-approval_QRcode.pdf",
    "title": "A Mechanistic Pharmacokinetic-Pharmacodynamic (PK-PD) Model of Quemliclustat (AB680), a Small-Molecule Inhibitor of CD73, in Healthy Volunteers and Patients with Gastrointestinal Malignancies",
    "date": "2022-03-01",
    "doc_type": "poster",
    "sha256": "ec53bb10cd554ad4aae7c0a04de03247a1a522ced922edf7eaf8aa7b6d51036d",
    "file_size_bytes": 3811633,
    "scraped_at": "2026-03-25T16:24:30.514544+00:00",
    "source_page": "https://arcusbio.com/our-science/publications/",
    "page_type": "publications"
  },
  "AB928_ASCPT_20220203_clean_final-approval_clean.pdf": {
    "source_url": "https://arcusbio.com/wp-content/uploads/2022/03/AB928_ASCPT_20220203_clean_final-approval_clean.pdf",
    "title": "Population Pharmacokinetics and Pharmacodynamics of Etrumadenant (AB928) in Healthy Volunteers and Cancer Patients",
    "date": "2022-03-01",
    "doc_type": "other",
    "sha256": "9c37bbd4e8f48663497d20fa684f2404d257d26852f115d60558cbe3c1b6a4ec",
    "file_size_bytes": 2291583,
    "scraped_at": "2026-03-25T16:24:30.722266+00:00",
    "source_page": "https://arcusbio.com/our-science/publications/",
    "page_type": "publications"
  },
  "lm_Arcus-Population-PK-AB122_ASCPT-poster-layout_final-model_cleanup_v2.pdf": {
    "source_url": "https://arcusbio.com/wp-content/uploads/2022/03/lm_Arcus-Population-PK-AB122_ASCPT-poster-layout_final-model_cleanup_v2.pdf",
    "title": "Population Pharmacokinetics of\u00a0Zimberelimab\u00a0(AB122) and Dose Justification by Model Informed Drug Development (MIDD) Approach",
    "date": "2022-03-01",
    "doc_type": "poster",
    "sha256": "39ea84d0adcd3888d63f72cffd078e4f7e3d93b7ff50f68888ea03ccb87e6179",
    "file_size_bytes": 1257014,
    "scraped_at": "2026-03-25T16:24:31.022858+00:00",
    "source_page": "https://arcusbio.com/our-science/publications/",
    "page_type": "publications"
  },
  "TAT2022_46P_Lawson.pdf": {
    "source_url": "https://arcusbio.com/wp-content/uploads/2022/03/TAT2022_46P_Lawson.pdf",
    "title": "AB521, a Clinical-Stage, Potent, and Selective Hypoxia-Inducible Factor (HIF)-2\u237a Inhibitor, for the Treatment of Renal Cell Carcinoma",
    "date": "2022-03-01",
    "doc_type": "other",
    "sha256": "c48599267b708592a2582a6c629832e3d3a383ca6ba76e98d5ea56a9bdf8bb33",
    "file_size_bytes": 577677,
    "scraped_at": "2026-03-25T16:24:31.106695+00:00",
    "source_page": "https://arcusbio.com/our-science/publications/",
    "page_type": "publications"
  },
  "2021-AB308-SITC-Poster.pdf": {
    "source_url": "https://arcusbio.com/wp-content/uploads/2021/11/2021-AB308-SITC-Poster.pdf",
    "title": "AB308 is an Anti-TIGIT Antibody That Enhances Immune Activation and Anti-Tumor Immunity Alone and in Combination With Other I-O Therapeutic Agent",
    "date": "2021-11-01",
    "doc_type": "poster",
    "sha256": "4829c592e07c928496931b24a9ed510ceb5360ec942806d23669028ac613ed6c",
    "file_size_bytes": 504634,
    "scraped_at": "2026-03-25T16:24:31.206843+00:00",
    "source_page": "https://arcusbio.com/our-science/publications/",
    "page_type": "publications"
  },
  "AXL-Poster-Presentation_2021-AACR-NCI-EORTC_Susan-Paprcka_Final.pdf": {
    "source_url": "https://arcusbio.com/wp-content/uploads/2021/10/AXL-Poster-Presentation_2021-AACR-NCI-EORTC_Susan-Paprcka_Final.pdf",
    "title": "Potent and selective AXL tyrosine kinase inhibition demonstrates significant anti-tumor efficacy in combination with standard of care therapeutics in preclinical models",
    "date": "2021-10-01",
    "doc_type": "poster",
    "sha256": "d22aac44f62bce7031127cec6cbd530f4452b8eff28d0cdb42c7e9db3f733d1a",
    "file_size_bytes": 1489127,
    "scraped_at": "2026-03-25T16:24:31.396164+00:00",
    "source_page": "https://arcusbio.com/our-science/publications/",
    "page_type": "publications"
  },
  "2021-AACR-NCI-EORTC-HIF2A-v2-Final.pdf": {
    "source_url": "https://arcusbio.com/wp-content/uploads/2022/10/2021-AACR-NCI-EORTC-HIF2A-v2-Final.pdf",
    "title": "AB521 potently and selectively inhibits pro-tumorigenic gene transcription by Hypoxia-Inducible Factor (HIF)-2\u237a in vitro and in vivo",
    "date": "2022-10-01",
    "doc_type": "poster",
    "sha256": "777581f3f6198e47d90dc34eec6c6f2c73042c469420a7c46520e519734d9500",
    "file_size_bytes": 693663,
    "scraped_at": "2026-03-25T16:24:31.550621+00:00",
    "source_page": "https://arcusbio.com/our-science/publications/",
    "page_type": "publications"
  },
  "SubudhiSK_ASCO_2021_ARC-6_poster_v5.0_07May2021_FINAL.pdf": {
    "source_url": "https://arcusbio.com/wp-content/uploads/2021/05/SubudhiSK_ASCO_2021_ARC-6_poster_v5.0_07May2021_FINAL.pdf",
    "title": "ARC-6: A Phase 1b/2, Open-Label, Randomized Platform Study to Evaluate Efficacy and Safety of Etrumadenant (AB928)-Based Treatment Combinations in Patients with Metastatic Castrate-Resistant Prostate Cancer",
    "date": "2021-05-01",
    "doc_type": "poster",
    "sha256": "02289c62b72df4464f5d3c90bc3f56d24814eaed725cec627ec9668fad4197e0",
    "file_size_bytes": 2718203,
    "scraped_at": "2026-03-25T16:24:31.679957+00:00",
    "source_page": "https://arcusbio.com/our-science/publications/",
    "page_type": "publications"
  },
  "AB521-Poster-AACR2021-Final.pdf": {
    "source_url": "https://arcusbio.com/wp-content/uploads/2021/04/AB521-Poster-AACR2021-Final.pdf",
    "title": "Discovery and characterization of AB521, a novel, potent, and selective hypoxia-inducible factor (HIF)-2\u237a inhibitor",
    "date": "2021-04-01",
    "doc_type": "poster",
    "sha256": "b77a3f9e30c36df7f1c160a95f513b3755a875ae056fc2de23b91f3bae3e6658",
    "file_size_bytes": 1737749,
    "scraped_at": "2026-03-25T16:24:31.787333+00:00",
    "source_page": "https://arcusbio.com/our-science/publications/",
    "page_type": "publications"
  },
  "Arcus-AACR-ARC-3-Poster_Final.pdf": {
    "source_url": "https://arcusbio.com/wp-content/uploads/2021/04/Arcus-AACR-ARC-3-Poster_Final.pdf",
    "title": "ARC-3: Updated results of Etrumadenant (AB928) + mFOLFOX-6 in patients with metastatic colorectal cancer",
    "date": "2021-04-01",
    "doc_type": "poster",
    "sha256": "bf32216fb3b933e25eceb27570af42a972ee62e8429a0e72558b3eacf66c1fa0",
    "file_size_bytes": 1140664,
    "scraped_at": "2026-03-25T16:24:31.926252+00:00",
    "source_page": "https://arcusbio.com/our-science/publications/",
    "page_type": "publications"
  },
  "Arcus-ASCO-GI-ARC-9-Poster_FINAL.pdf": {
    "source_url": "https://arcusbio.com/wp-content/uploads/2021/01/Arcus-ASCO-GI-ARC-9-Poster_FINAL.pdf",
    "title": "ARC-9: Phase 1b/2 Study to Evaluate Etrumadenant (AB928)-Based Treatment Combinations in Patients with Metastatic Colorectal Cancer",
    "date": "2021-01-01",
    "doc_type": "poster",
    "sha256": "12edbebfbf8b41f7d82a789c56c068ad72fb7b903f8848f8fc80697c55dc9b64",
    "file_size_bytes": 1014814,
    "scraped_at": "2026-03-25T16:24:32.074184+00:00",
    "source_page": "https://arcusbio.com/our-science/publications/",
    "page_type": "publications"
  },
  "Arcus-ASCO-GI-ARC-8-Poster_13January2021.pdf": {
    "source_url": "https://arcusbio.com/wp-content/uploads/2021/01/Arcus-ASCO-GI-ARC-8-Poster_13January2021.pdf",
    "title": "ARC-8: Phase 1/1b Study to Evaluate Safety and Tolerability of\u00a0 AB680 + Chemotherapy + Zimberelimab (AB122) in Patients with Treatment-Naive Metastatic Pancreatic Adenocarcinoma",
    "date": "2021-01-01",
    "doc_type": "poster",
    "sha256": "c78258a2f43bec73e353bfa625bd2950930bb22c817ff11c6e43032d86388530",
    "file_size_bytes": 3792562,
    "scraped_at": "2026-03-25T16:24:32.205143+00:00",
    "source_page": "https://arcusbio.com/our-science/publications/",
    "page_type": "publications"
  },
  "ARC-2-SABCS-2020_final-poster-1.pdf": {
    "source_url": "https://arcusbio.com/wp-content/uploads/2020/12/ARC-2-SABCS-2020_final-poster-1.pdf",
    "title": "ARC-2: Efficacy and Safety of Etrumadenant (AB928) + Pegylated Liposomal Doxorubicin (PLD) \u00b1 Eganelisib (IPI-549) in Participants with Metastatic Ovarian and Triple Negative Breast Cancer",
    "date": "2020-12-01",
    "doc_type": "poster",
    "sha256": "f6fdbd681d7107bbe51665992b7c53063b43d5a0ca475348753b9c1de82c671b",
    "file_size_bytes": 3192578,
    "scraped_at": "2026-03-25T16:24:32.372739+00:00",
    "source_page": "https://arcusbio.com/our-science/publications/",
    "page_type": "publications"
  },
  "HIF-2a-SITC.2020-POSTER-FINAL.pdf": {
    "source_url": "https://arcusbio.com/wp-content/uploads/2020/11/HIF-2a-SITC.2020-POSTER-FINAL.pdf",
    "title": "Novel, Potent, and Selective Inhibitors of Hypoxia-Inducible Factor (HIF)-2\u03b1 Reverse Pro-tumorigenic Transcriptional Programming in Cancer, Stromal, and Immune Cells",
    "date": "2020-11-01",
    "doc_type": "poster",
    "sha256": "6cc9e4516ebc00145e65577ff75b9e8b473dc1c5ba53eedcbafd86c5b2eae39b",
    "file_size_bytes": 1609579,
    "scraped_at": "2026-03-25T16:24:32.480782+00:00",
    "source_page": "https://arcusbio.com/our-science/publications/",
    "page_type": "publications"
  },
  "AXL-SITC.2020-FINAL-POSTER.pdf": {
    "source_url": "https://arcusbio.com/wp-content/uploads/2020/11/AXL-SITC.2020-FINAL-POSTER.pdf",
    "title": "Potent and Selective Inhibition of AXL Receptor Tyrosine Kinase for the Treatment of Cancer",
    "date": "2020-11-01",
    "doc_type": "poster",
    "sha256": "35117032455fceb5675a4f59f2c84e7ba362e5724dcc2bb2f0ab8669fd97bf1f",
    "file_size_bytes": 1192482,
    "scraped_at": "2026-03-25T16:24:32.609429+00:00",
    "source_page": "https://arcusbio.com/our-science/publications/",
    "page_type": "publications"
  },
  "ARC3_poster_FINAL-Presented.pdf": {
    "source_url": "https://arcusbio.com/wp-content/uploads/2020/11/ARC3_poster_FINAL-Presented.pdf",
    "title": "Emerging Insights on the Association of Tumor Molecular Phenotype with Clinical Benefit in Metastatic Colorectal Cancer (mCRC) Subjects Treated with AB928 + Modified FOLFOX-6 (mFOLFOX-6)",
    "date": "2020-11-01",
    "doc_type": "poster",
    "sha256": "ac09cf7b8af2a7d5485148fe2ac737854327a964e507cf8a2ffee63f3ba747e8",
    "file_size_bytes": 5100244,
    "scraped_at": "2026-03-25T16:24:32.824373+00:00",
    "source_page": "https://arcusbio.com/our-science/publications/",
    "page_type": "publications"
  },
  "HIF-2a-Poster-ENA.2020-FINAL.pdf": {
    "source_url": "https://arcusbio.com/wp-content/uploads/2020/11/HIF-2a-Poster-ENA.2020-FINAL.pdf",
    "title": "Discovery and Characterization of Novel, Potent, and Selective Hypoxia-Inducible Factor (HIF)-2a Inhibitors",
    "date": "2020-11-01",
    "doc_type": "poster",
    "sha256": "02061e5378c49f436894cfa66c43486550e20737c305a3e8dcfdf78dd3e6d064",
    "file_size_bytes": 1352842,
    "scraped_at": "2026-03-25T16:24:32.948029+00:00",
    "source_page": "https://arcusbio.com/our-science/publications/",
    "page_type": "publications"
  },
  "AXL-Poster-ENA.2020-FINAL.pdf": {
    "source_url": "https://arcusbio.com/wp-content/uploads/2020/11/AXL-Poster-ENA.2020-FINAL.pdf",
    "title": "Discovery and Characterization of Potent and Selective AXL Receptor Tyrosine Kinase Inhibitors for Cancer Therapy",
    "date": "2020-11-01",
    "doc_type": "poster",
    "sha256": "af80c5e453886c52a361614260b484639e99320aef1a22e8d71bc2076cdafff7",
    "file_size_bytes": 639493,
    "scraped_at": "2026-03-25T16:24:33.121816+00:00",
    "source_page": "https://arcusbio.com/our-science/publications/",
    "page_type": "publications"
  },
  "ARC-4_ESMO_2020_poster_FINAL.pdf": {
    "source_url": "https://arcusbio.com/wp-content/uploads/2020/09/ARC-4_ESMO_2020_poster_FINAL.pdf",
    "title": "ARC-4: Efficacy and Safety of Etrumadenant (AB928) plus Carboplatin, Pemetrexed and a PD-1 Antibody in Participants with Metastatic Non-Small Cell Lung Cancer",
    "date": "2020-09-01",
    "doc_type": "poster",
    "sha256": "63f4f341021b703364f0e7ef9702afb6f2be7bf8133ae49b205b1ad7eda1ccce",
    "file_size_bytes": 3064904,
    "scraped_at": "2026-03-25T16:24:33.273107+00:00",
    "source_page": "https://arcusbio.com/our-science/publications/",
    "page_type": "publications"
  },
  "ARC-6_ESMO_2020_poster_FINAL.pdf": {
    "source_url": "https://arcusbio.com/wp-content/uploads/2020/09/ARC-6_ESMO_2020_poster_FINAL.pdf",
    "title": "ARC-6: A Phase 1b/2, Open-Label, Randomized Platform Study Evaluating the Efficacy and Safety of Etrumadenant (AB928)-Based Treatment Combinations in Patients with Metastatic Castrate-Resistant Prostate Cancer",
    "date": "2020-09-01",
    "doc_type": "poster",
    "sha256": "2358336d3f1b132fd2b3f6751b25c741f7924de0c688ed4d0f8166ac39670fdf",
    "file_size_bytes": 3494739,
    "scraped_at": "2026-03-25T16:24:33.410880+00:00",
    "source_page": "https://arcusbio.com/our-science/publications/",
    "page_type": "publications"
  },
  "ARC-7_ESMO_2020_poster_FINAL.pdf": {
    "source_url": "https://arcusbio.com/wp-content/uploads/2020/09/ARC-7_ESMO_2020_poster_FINAL.pdf",
    "title": "ARC-7: A Phase 2 Study to Evaluate the Safety and Efficacy of Zimberelimab Monotherapy and Domvanalimab (AB154) + Zimberelimab +/- Etrumadenant (AB928) in Front-Line, PD-L1-High Expressing, Non-Small Cell Lung Cancer",
    "date": "2020-09-01",
    "doc_type": "poster",
    "sha256": "3d2591dc61a049b2ef699289a7d87a708916088dec33775b3d53a43f26a43dbe",
    "file_size_bytes": 3321407,
    "scraped_at": "2026-03-25T16:24:33.537382+00:00",
    "source_page": "https://arcusbio.com/our-science/publications/",
    "page_type": "publications"
  },
  "AACR-Poster-LB-387-Cecchini-et-al.pdf": {
    "source_url": "https://arcusbio.com/wp-content/uploads/2020/09/AACR-Poster-LB-387-Cecchini-et-al.pdf",
    "title": "Poster: Efficacy and safety of etrumadenant plus modified FOLFOX-6 in participants with metastatic colorectal cancer: initial results at the recommended dose for expansion (ARC-3).",
    "date": "2020-09-01",
    "doc_type": "poster",
    "sha256": "ca6b33ee03b2eef178918a69f26da6b6158f69e6244e3c4cc91ebff953a37643",
    "file_size_bytes": 3118092,
    "scraped_at": "2026-03-25T16:24:33.839114+00:00",
    "source_page": "https://arcusbio.com/our-science/publications/",
    "page_type": "publications"
  },
  "ASCO-GU-2020-TIP-Poster_FINAL-13FEB20.pdf": {
    "source_url": "https://arcusbio.com/wp-content/uploads/2020/09/ASCO-GU-2020-TIP-Poster_FINAL-13FEB20.pdf",
    "title": "A phase 1b/2, open-label, platform study evaluating the efficacy and safety of etrumadenant-based treatment combinations in participants with metastatic castrate resistant prostate cancer (ARC-6).",
    "date": "2020-09-01",
    "doc_type": "poster",
    "sha256": "937e3982f913d8a24598b3decf5355364d617b7d2136f1931da0e3892d6d7ad4",
    "file_size_bytes": 689938,
    "scraped_at": "2026-03-25T16:24:33.921506+00:00",
    "source_page": "https://arcusbio.com/our-science/publications/",
    "page_type": "publications"
  },
  "a-phase-1-study-to-evaluate-the-safety-and-tolerability-of-AB680-combination-therapy-in-participants-with-gastrointestinal.pdf": {
    "source_url": "https://arcusbio.com/wp-content/uploads/2020/09/a-phase-1-study-to-evaluate-the-safety-and-tolerability-of-AB680-combination-therapy-in-participants-with-gastrointestinal.pdf",
    "title": "A phase 1 study to evaluate the safety and tolerability of AB680 combination therapy in participants with gastrointestinal malignancies (ARC-8).",
    "date": "2020-09-01",
    "doc_type": "other",
    "sha256": "8805d7e554fa9b8584157d01bb1e17d26aa8685b0b21d24c0c4a137f52f0c94d",
    "file_size_bytes": 778414,
    "scraped_at": "2026-03-25T16:24:34.049463+00:00",
    "source_page": "https://arcusbio.com/our-science/publications/",
    "page_type": "publications"
  },
  "20200115-Keystone-Hypoxia-Poster_final.pdf": {
    "source_url": "https://arcusbio.com/wp-content/uploads/2020/09/20200115-Keystone-Hypoxia-Poster_final.pdf",
    "title": "Selective inhibition of hypoxia-inducible factor (HIF)-2\u03b1 for the treatment of cancer.",
    "date": "2020-09-01",
    "doc_type": "poster",
    "sha256": "a4a70625d20255f886ff00fe2c71611a10bc0f9af7e25cd3f5e9507017cdffd4",
    "file_size_bytes": 1875341,
    "scraped_at": "2026-03-25T16:24:34.190098+00:00",
    "source_page": "https://arcusbio.com/our-science/publications/",
    "page_type": "publications"
  },
  "2019-SITC-Myeloid-Presented.pdf": {
    "source_url": "https://arcusbio.com/wp-content/uploads/2020/09/2019-SITC-Myeloid-Presented.pdf",
    "title": "Targeting immune-suppressive myeloid cell pathways for the treatment of cancer.",
    "date": "2020-09-01",
    "doc_type": "other",
    "sha256": "86b963c42978ac7075fab6df68e6c7bf7f71d9f4d354c48acfc163518eececce",
    "file_size_bytes": 445869,
    "scraped_at": "2026-03-25T16:24:34.413520+00:00",
    "source_page": "https://arcusbio.com/our-science/publications/",
    "page_type": "publications"
  },
  "2019-SITC-AB154-Presented.pdf": {
    "source_url": "https://arcusbio.com/wp-content/uploads/2020/09/2019-SITC-AB154-Presented.pdf",
    "title": "Characterization of domvanalimab, a humanized, non-depleting \u03b1-TIGIT antibody undergoing clinical evaluation in subjects with advanced solid tumors.",
    "date": "2020-09-01",
    "doc_type": "other",
    "sha256": "c95e2e04fc041018411d8d7e90d1ada5b44e2343b407cd07b5320d7c85c85b4d",
    "file_size_bytes": 1691091,
    "scraped_at": "2026-03-25T16:24:34.702526+00:00",
    "source_page": "https://arcusbio.com/our-science/publications/",
    "page_type": "publications"
  },
  "2019-SITC-AB680-Presented.pdf": {
    "source_url": "https://arcusbio.com/wp-content/uploads/2020/09/2019-SITC-AB680-Presented.pdf",
    "title": "Phase 1 safety trial in healthy volunteers of Quemliclustat (AB680), a small molecule inhibitor of CD73 and rationale for combination therapy in patients with gastrointestinal malignancies.",
    "date": "2020-09-01",
    "doc_type": "other",
    "sha256": "afd3f6561d935b191cbbd4da68283bb842716295610756ed89bf8f0d461841e1",
    "file_size_bytes": 11806461,
    "scraped_at": "2026-03-25T16:24:34.988759+00:00",
    "source_page": "https://arcusbio.com/our-science/publications/",
    "page_type": "publications"
  },
  "2019-SITC-AB928-Presented.pdf": {
    "source_url": "https://arcusbio.com/wp-content/uploads/2020/09/2019-SITC-AB928-Presented.pdf",
    "title": "A2bR contributes to adenosine-mediated immunosuppression, which is relieved by the dual A2a/A2bantagonist etrumadenant.",
    "date": "2020-09-01",
    "doc_type": "other",
    "sha256": "0a03d7fc7548b82bbdeaa1729a8c941cb2eca1cdc04d8f1de18208074cc9cfe2",
    "file_size_bytes": 4732798,
    "scraped_at": "2026-03-25T16:24:35.272337+00:00",
    "source_page": "https://arcusbio.com/our-science/publications/",
    "page_type": "publications"
  },
  "novel-potent-and-selective-hypoxia-inducible-factor-2a-HIF-2a-antagonists.pdf": {
    "source_url": "https://arcusbio.com/wp-content/uploads/2020/09/novel-potent-and-selective-hypoxia-inducible-factor-2a-HIF-2a-antagonists.pdf",
    "title": "Novel, potent, and selective hypoxia-inducible factor-2\u03b1 (HIF-2\u03b1) antagonists.",
    "date": "2020-09-01",
    "doc_type": "other",
    "sha256": "c81d258037144ba2a0cf0cc082cd7a5d5e484eae3d01c8aab0dbec15c4e566b3",
    "file_size_bytes": 2586206,
    "scraped_at": "2026-03-25T16:24:35.544511+00:00",
    "source_page": "https://arcusbio.com/our-science/publications/",
    "page_type": "publications"
  },
  "AB928_ESMO_Poster_FINAL.pdf": {
    "source_url": "https://arcusbio.com/wp-content/uploads/2020/09/AB928_ESMO_Poster_FINAL.pdf",
    "title": "Phase 1 evaluation of etrumadenant, a novel dual adenosine receptor antagonist, combined with chemotherapy or AB122 (anti-PD-1) in patients (pts) with advanced malignancies.",
    "date": "2020-09-01",
    "doc_type": "poster",
    "sha256": "a2d2bbcf7a64377f0e79cf4d46d76305d3df9381ef94a14debdf6d64e4b633b7",
    "file_size_bytes": 576931,
    "scraped_at": "2026-03-25T16:24:35.743237+00:00",
    "source_page": "https://arcusbio.com/our-science/publications/",
    "page_type": "publications"
  },
  "Arcus-ASCO-Poster-May-2019_FINAL.pdf": {
    "source_url": "https://arcusbio.com/wp-content/uploads/2020/09/Arcus-ASCO-Poster-May-2019_FINAL.pdf",
    "title": "Etrumadenant, a novel dual adenosine receptor antagonist, combined with chemotherapy or AB122 (anti-PD-1) in patients with advanced tumors: preliminary results from ongoing phase 1 studies.",
    "date": "2020-09-01",
    "doc_type": "poster",
    "sha256": "901b6b9788fe32e55d99426f8da4151aaf73c1b24165b490820051b668358831",
    "file_size_bytes": 328489,
    "scraped_at": "2026-03-25T16:24:35.824363+00:00",
    "source_page": "https://arcusbio.com/our-science/publications/",
    "page_type": "publications"
  },
  "AACR-PACT-Poster-Peng-II-2019-03-29.pdf": {
    "source_url": "https://arcusbio.com/wp-content/uploads/2020/09/AACR-PACT-Poster-Peng-II-2019-03-29.pdf",
    "title": "Longitudinal monitoring of neoepitope-specific T cell repertoires in patient blood following cancer immunotherapy.",
    "date": "2020-09-01",
    "doc_type": "poster",
    "sha256": "38245351d36b2dcc65a0cad0e0744f990df7c1259fec2525b5067f08b48ddb6e",
    "file_size_bytes": 1864177,
    "scraped_at": "2026-03-25T16:24:35.937016+00:00",
    "source_page": "https://arcusbio.com/our-science/publications/",
    "page_type": "publications"
  },
  "AB122-RO-PACT-Analysis-AACR-2019.pdf": {
    "source_url": "https://arcusbio.com/wp-content/uploads/2020/09/AB122-RO-PACT-Analysis-AACR-2019.pdf",
    "title": "Receptor occupancy and neo-epitope specific T-cell repertoires in patients with solid tissue tumors following anti-PD-1 therapy.",
    "date": "2020-09-01",
    "doc_type": "poster",
    "sha256": "e51687c48284f805390e9141a2822380358a98c12595a39efb0bee069d4f2012",
    "file_size_bytes": 737385,
    "scraped_at": "2026-03-25T16:24:36.134170+00:00",
    "source_page": "https://arcusbio.com/our-science/publications/",
    "page_type": "publications"
  },
  "AACR-2019-Biomarkers-poster.pdf": {
    "source_url": "https://arcusbio.com/wp-content/uploads/2020/09/AACR-2019-Biomarkers-poster.pdf",
    "title": "Methods for assessment of the \u201cadenosine fingerprint\u201d in clinical trials of etrumadenant.",
    "date": "2020-09-01",
    "doc_type": "poster",
    "sha256": "7dd5d0be268bd563229d381c31ee807e1d0bab57ab4bab627423d4c315010887",
    "file_size_bytes": 1862932,
    "scraped_at": "2026-03-25T16:24:36.282441+00:00",
    "source_page": "https://arcusbio.com/our-science/publications/",
    "page_type": "publications"
  },
  "inhibiting-CD73-and-KRAS-enhances-the-effect-of-anti-PD-1-therapy-in-a-KRASG12C-TP53R172H-pancreatic-cancer-model.pdf": {
    "source_url": "https://arcusbio.com/wp-content/uploads/2020/09/inhibiting-CD73-and-KRAS-enhances-the-effect-of-anti-PD-1-therapy-in-a-KRASG12C-TP53R172H-pancreatic-cancer-model.pdf",
    "title": "Inhibiting CD73 and KRAS enhances the effect of anti-PD-1 therapy in a KRASG12C/TP53R172H/+pancreatic cancer model.",
    "date": "2020-09-01",
    "doc_type": "other",
    "sha256": "fbc3a0c4802439c2e46aa6636497f2ab5b8ee8c22695080a00c333d28446672d",
    "file_size_bytes": 11079805,
    "scraped_at": "2026-03-25T16:24:36.812244+00:00",
    "source_page": "https://arcusbio.com/our-science/publications/",
    "page_type": "publications"
  },
  "2019.03.25-AACR-2019-AB154-Poster-AA-FINAL.pdf": {
    "source_url": "https://arcusbio.com/wp-content/uploads/2020/09/2019.03.25-AACR-2019-AB154-Poster-AA-FINAL.pdf",
    "title": "Characterization of domvanalimab, a humanized \u03b1-TIGIT antibody, for use in combination therapies.",
    "date": "2020-09-01",
    "doc_type": "poster",
    "sha256": "8867118d1281e48776beee7f3ed0840d62bf02bad1b96da6604a4c2bd6f6bc46",
    "file_size_bytes": 1444991,
    "scraped_at": "2026-03-25T16:24:36.921582+00:00",
    "source_page": "https://arcusbio.com/our-science/publications/",
    "page_type": "publications"
  },
  "AACR-2019-ARG1-SCE-Final-Draft-4.pdf": {
    "source_url": "https://arcusbio.com/wp-content/uploads/2020/09/AACR-2019-ARG1-SCE-Final-Draft-4.pdf",
    "title": "AB474, a potent orally bioavailable inhibitor of arginase, for the treatment of cancer.",
    "date": "2020-09-01",
    "doc_type": "poster",
    "sha256": "6eee2aa9f8a8bb32e0375aaac58c3bdda1db66cce5a149e02ba9a76163d75add",
    "file_size_bytes": 642085,
    "scraped_at": "2026-03-25T16:24:37.124789+00:00",
    "source_page": "https://arcusbio.com/our-science/publications/",
    "page_type": "publications"
  },
  "Adenosine_PanRAS_EGFR-Relationship-Akshata-AACR-2019-1.pdf": {
    "source_url": "https://arcusbio.com/wp-content/uploads/2020/09/Adenosine_PanRAS_EGFR-Relationship-Akshata-AACR-2019-1.pdf",
    "title": "Altered pan-Ras pathway and activating mutations in EGFR result in elevated CD73 in multiple cancers.",
    "date": "2020-09-01",
    "doc_type": "poster",
    "sha256": "9576fc85c0271d5dd69ca0242c2f77555c62551a256fbe1d6497562ad9098291",
    "file_size_bytes": 3691655,
    "scraped_at": "2026-03-25T16:24:37.374439+00:00",
    "source_page": "https://arcusbio.com/our-science/publications/",
    "page_type": "publications"
  },
  "oncogene-driven-regulation-of-adenosine-pathway-expression-in-multiple-cancers.pdf": {
    "source_url": "https://arcusbio.com/wp-content/uploads/2020/09/oncogene-driven-regulation-of-adenosine-pathway-expression-in-multiple-cancers.pdf",
    "title": "Oncogene-driven regulation of adenosine pathway expression in multiple cancers.",
    "date": "2020-09-01",
    "doc_type": "other",
    "sha256": "4604fa290dd7e08ca1a2986be134172a8e8b8f704c8cd5e4f849a61fbbf61f08",
    "file_size_bytes": 3436414,
    "scraped_at": "2026-03-25T16:24:37.537023+00:00",
    "source_page": "https://arcusbio.com/our-science/publications/",
    "page_type": "publications"
  },
  "development-of-biomarkers-to-assess-adenosine-generation-activity-in-support-of-clinical-trials-conducted-with-the-adenos.pdf": {
    "source_url": "https://arcusbio.com/wp-content/uploads/2020/09/development-of-biomarkers-to-assess-adenosine-generation-activity-in-support-of-clinical-trials-conducted-with-the-adenos.pdf",
    "title": "Development of biomarkers to assess adenosine generation & activity in support of clinical trials conducted with the adenosine receptor antagonist etrumadenant.",
    "date": "2020-09-01",
    "doc_type": "other",
    "sha256": "cd0895ca353f9c3e733ab0456e2aec64c9bf7d94daaab4258cad4aed55dbb00a",
    "file_size_bytes": 1537772,
    "scraped_at": "2026-03-25T16:24:37.648005+00:00",
    "source_page": "https://arcusbio.com/our-science/publications/",
    "page_type": "publications"
  },
  "selection-of-optimized-drug-candidates-dosing-regimen-pharmacodynamic-endpoints-tumor-types-and-biomarkers.pdf": {
    "source_url": "https://arcusbio.com/wp-content/uploads/2020/09/selection-of-optimized-drug-candidates-dosing-regimen-pharmacodynamic-endpoints-tumor-types-and-biomarkers.pdf",
    "title": "Selection of optimized drug candidates, dosing regimen, pharmacodynamic endpoints, tumor types, and biomarkers for translating inhibition of the adenosine pathway into effective anti-tumor activity.",
    "date": "2020-09-01",
    "doc_type": "other",
    "sha256": "c5468e947bd9d46b8e5920cd4763e81fcee63c9a8fba85e683ca8bb97c034dce",
    "file_size_bytes": 1858306,
    "scraped_at": "2026-03-25T16:24:37.861599+00:00",
    "source_page": "https://arcusbio.com/our-science/publications/",
    "page_type": "publications"
  },
  "poster-No.-P15-abstract-No.-10495.pdf": {
    "source_url": "https://arcusbio.com/wp-content/uploads/2020/09/poster-No.-P15-abstract-No.-10495.pdf",
    "title": "Development of a robust, simplified method to measure receptor occupancy in peripheral blood from patients treated with a novel anti-PD-1 agent, AB122.",
    "date": "2020-09-01",
    "doc_type": "poster",
    "sha256": "671b81df1e10948e1e8d1c719b040a0a31d2b7675bfbf394e5f39de91f7b7179",
    "file_size_bytes": 1255018,
    "scraped_at": "2026-03-25T16:24:37.964047+00:00",
    "source_page": "https://arcusbio.com/our-science/publications/",
    "page_type": "publications"
  },
  "poster-No.-P697-abstract-No.-10538.aee63cc8.pdf": {
    "source_url": "https://arcusbio.com/wp-content/uploads/2020/09/poster-No.-P697-abstract-No.-10538.aee63cc8.pdf",
    "title": "Preclinical characterization of domvanalimab, a fully humanized anti-TIGIT antibody, for use in combination therapies.",
    "date": "2020-09-01",
    "doc_type": "poster",
    "sha256": "f39a66507b0e362ae3582c097089f83b10a16c741e7c5feabd5f115733996912",
    "file_size_bytes": 884263,
    "scraped_at": "2026-03-25T16:24:38.067478+00:00",
    "source_page": "https://arcusbio.com/our-science/publications/",
    "page_type": "publications"
  }
}